acconeer/exptool/__init__.py
acconeer/exptool/_bs_thread.py
acconeer/exptool/_cli.py
acconeer/exptool/_qt_bindings_canary.py
acconeer/exptool/_version.py
acconeer/exptool/libft4222.py
acconeer/exptool/mpl_process.py
acconeer/exptool/pg_process.py
acconeer/exptool/py.typed
acconeer/exptool/utils.py
acconeer/exptool/_core/__init__.py
acconeer/exptool/_core/docstrings.py
acconeer/exptool/_core/int_16_complex.py
acconeer/exptool/_core/version_parsing.py
acconeer/exptool/_core/class_creation/__init__.py
acconeer/exptool/_core/class_creation/attrs.py
acconeer/exptool/_core/class_creation/descriptors.py
acconeer/exptool/_core/class_creation/enum.py
acconeer/exptool/_core/class_creation/formatting.py
acconeer/exptool/_core/communication/__init__.py
acconeer/exptool/_core/communication/client.py
acconeer/exptool/_core/communication/comm_devices.py
acconeer/exptool/_core/communication/message_stream.py
acconeer/exptool/_core/communication/unwrap_ticks.py
acconeer/exptool/_core/communication/communication_protocol/__init__.py
acconeer/exptool/_core/communication/communication_protocol/protocol.py
acconeer/exptool/_core/communication/communication_protocol/messages/__init__.py
acconeer/exptool/_core/communication/communication_protocol/messages/erroneus_message.py
acconeer/exptool/_core/communication/communication_protocol/messages/log_message.py
acconeer/exptool/_core/communication/communication_protocol/messages/message.py
acconeer/exptool/_core/communication/communication_protocol/messages/set_baudrate_response.py
acconeer/exptool/_core/communication/communication_protocol/messages/streaming_responses.py
acconeer/exptool/_core/communication/communication_protocol/messages/system_info_response.py
acconeer/exptool/_core/communication/links/__init__.py
acconeer/exptool/_core/communication/links/buffered_link.py
acconeer/exptool/_core/communication/links/helpers.py
acconeer/exptool/_core/communication/links/null_link.py
acconeer/exptool/_core/communication/links/serial_link.py
acconeer_exptool-7.17.4.dist-info/METADATA
acconeer_exptool-7.17.4.dist-info/WHEEL
acconeer_exptool-7.17.4.dist-info/licenses/LICENSE.md
acconeer_exptool-7.17.4.dist-info/RECORD
