Metadata-Version: 2.4
Name: acconeer-exptool
Version: 7.17.4
Summary: Acconeer Exploration Tool
Project-URL: Documentation, https://docs.acconeer.com
Project-URL: Homepage, https://github.com/acconeer/acconeer-python-exploration
Project-URL: Source, https://github.com/acconeer/acconeer-python-exploration
Project-URL: Tracker, https://github.com/acconeer/acconeer-python-exploration/issues
Author-email: Acconeer AB <tools@acconeer.com>
License-Expression: BSD-3-Clause-Clear
License-File: LICENSE.md
Classifier: Programming Language :: Python
Classifier: Programming Language :: Python :: 3
Classifier: Programming Language :: Python :: 3 :: Only
Classifier: Programming Language :: Python :: 3.9
Classifier: Programming Language :: Python :: 3.10
Classifier: Programming Language :: Python :: 3.11
Classifier: Programming Language :: Python :: 3.12
Classifier: Programming Language :: Python :: 3.13
Requires-Python: >=3.9
Requires-Dist: attributes-doc==0.4.0
Requires-Dist: attrs>=22.1.0
Requires-Dist: cbor2
Requires-Dist: exceptiongroup==1.1.1
Requires-Dist: h5py<4,>=3.8
Requires-Dist: libusb-package==1.0.26.3
Requires-Dist: numpy>=1.20
Requires-Dist: packaging
Requires-Dist: pandas>=1.3.5
Requires-Dist: platformdirs
Requires-Dist: pyserial>=3.5
Requires-Dist: pyusb>=1.2.1
Requires-Dist: pyyaml
Requires-Dist: requests<3,>=2.0
Requires-Dist: textual==0.1.18
Requires-Dist: typing-extensions<5,>=4
Requires-Dist: xlsxwriter>=3.1.9
Provides-Extra: algo
Requires-Dist: scipy; extra == 'algo'
Provides-Extra: app
Requires-Dist: bs4; extra == 'app'
Requires-Dist: docutils!=0.18,>=0.17; extra == 'app'
Requires-Dist: matplotlib>3.5.1; extra == 'app'
Requires-Dist: psutil; extra == 'app'
Requires-Dist: pyperclip; extra == 'app'
Requires-Dist: pyqtdarktheme; extra == 'app'
Requires-Dist: pyqtgraph==0.13.7; extra == 'app'
Requires-Dist: pyside6==6.8.3; extra == 'app'
Requires-Dist: qtawesome; extra == 'app'
Requires-Dist: qtpy>=2.3.0; extra == 'app'
Requires-Dist: scipy; extra == 'app'
Provides-Extra: docs
Requires-Dist: docutils!=0.18,>=0.17; extra == 'docs'
Requires-Dist: myst-parser>=2.0.0; extra == 'docs'
Requires-Dist: scipy; extra == 'docs'
Requires-Dist: sphinx-book-theme==1.1.2; extra == 'docs'
Requires-Dist: sphinx-design; extra == 'docs'
Requires-Dist: sphinx-notfound-page>=1.0.0; extra == 'docs'
Requires-Dist: sphinx-tabs; extra == 'docs'
Requires-Dist: sphinx>=7.2.6; extra == 'docs'
Requires-Dist: sphinxcontrib-spelling; extra == 'docs'
Requires-Dist: sphinxcontrib-youtube; extra == 'docs'
Requires-Dist: sphinxext-rediraffe; extra == 'docs'
